<annotation>
	<folder>dataset_images</folder>
	<filename>worker (553).jpg</filename>
	<path>D:\Workspace\YOLO_annotation\dataset_images\worker (553).jpg</path>
	<source>
		<database>Unknown</database>
	</source>
	<size>
		<width>194</width>
		<height>259</height>
		<depth>3</depth>
	</size>
	<segmented>0</segmented>
	<object>
		<name>helmet</name>
		<pose>Unspecified</pose>
		<truncated>0</truncated>
		<difficult>0</difficult>
		<bndbox>
			<xmin>104</xmin>
			<ymin>82</ymin>
			<xmax>140</xmax>
			<ymax>107</ymax>
		</bndbox>
	</object>
	<object>
		<name>person with helmet</name>
		<pose>Unspecified</pose>
		<truncated>0</truncated>
		<difficult>0</difficult>
		<bndbox>
			<xmin>88</xmin>
			<ymin>83</ymin>
			<xmax>150</xmax>
			<ymax>257</ymax>
		</bndbox>
	</object>
</annotation>
