<annotation>
	<folder>all_images_folder</folder>
	<filename>worker (839).jpg</filename>
	<path>C:\Users\nasir.shah\Desktop\all_images_folder\all_images_folder\worker (839).jpg</path>
	<source>
		<database>Unknown</database>
	</source>
	<size>
		<width>245</width>
		<height>205</height>
		<depth>3</depth>
	</size>
	<segmented>0</segmented>
	<object>
		<name>person without helmet</name>
		<pose>Unspecified</pose>
		<truncated>0</truncated>
		<difficult>0</difficult>
		<bndbox>
			<xmin>25</xmin>
			<ymin>29</ymin>
			<xmax>61</xmax>
			<ymax>179</ymax>
		</bndbox>
	</object>
	<object>
		<name>person without helmet</name>
		<pose>Unspecified</pose>
		<truncated>0</truncated>
		<difficult>0</difficult>
		<bndbox>
			<xmin>58</xmin>
			<ymin>29</ymin>
			<xmax>84</xmax>
			<ymax>176</ymax>
		</bndbox>
	</object>
	<object>
		<name>person without helmet</name>
		<pose>Unspecified</pose>
		<truncated>0</truncated>
		<difficult>0</difficult>
		<bndbox>
			<xmin>79</xmin>
			<ymin>16</ymin>
			<xmax>99</xmax>
			<ymax>54</ymax>
		</bndbox>
	</object>
	<object>
		<name>person without helmet</name>
		<pose>Unspecified</pose>
		<truncated>0</truncated>
		<difficult>0</difficult>
		<bndbox>
			<xmin>98</xmin>
			<ymin>28</ymin>
			<xmax>115</xmax>
			<ymax>178</ymax>
		</bndbox>
	</object>
	<object>
		<name>person without helmet</name>
		<pose>Unspecified</pose>
		<truncated>0</truncated>
		<difficult>0</difficult>
		<bndbox>
			<xmin>112</xmin>
			<ymin>19</ymin>
			<xmax>132</xmax>
			<ymax>53</ymax>
		</bndbox>
	</object>
	<object>
		<name>person without helmet</name>
		<pose>Unspecified</pose>
		<truncated>0</truncated>
		<difficult>0</difficult>
		<bndbox>
			<xmin>128</xmin>
			<ymin>28</ymin>
			<xmax>146</xmax>
			<ymax>153</ymax>
		</bndbox>
	</object>
	<object>
		<name>person without helmet</name>
		<pose>Unspecified</pose>
		<truncated>0</truncated>
		<difficult>0</difficult>
		<bndbox>
			<xmin>144</xmin>
			<ymin>21</ymin>
			<xmax>160</xmax>
			<ymax>53</ymax>
		</bndbox>
	</object>
	<object>
		<name>person without helmet</name>
		<pose>Unspecified</pose>
		<truncated>0</truncated>
		<difficult>0</difficult>
		<bndbox>
			<xmin>193</xmin>
			<ymin>28</ymin>
			<xmax>230</xmax>
			<ymax>147</ymax>
		</bndbox>
	</object>
	<object>
		<name>helmet</name>
		<pose>Unspecified</pose>
		<truncated>0</truncated>
		<difficult>0</difficult>
		<bndbox>
			<xmin>169</xmin>
			<ymin>17</ymin>
			<xmax>190</xmax>
			<ymax>31</ymax>
		</bndbox>
	</object>
	<object>
		<name>helmet</name>
		<pose>Unspecified</pose>
		<truncated>0</truncated>
		<difficult>0</difficult>
		<bndbox>
			<xmin>158</xmin>
			<ymin>29</ymin>
			<xmax>176</xmax>
			<ymax>42</ymax>
		</bndbox>
	</object>
	<object>
		<name>person with helmet</name>
		<pose>Unspecified</pose>
		<truncated>0</truncated>
		<difficult>0</difficult>
		<bndbox>
			<xmin>158</xmin>
			<ymin>31</ymin>
			<xmax>178</xmax>
			<ymax>178</ymax>
		</bndbox>
	</object>
	<object>
		<name>person with helmet</name>
		<pose>Unspecified</pose>
		<truncated>0</truncated>
		<difficult>0</difficult>
		<bndbox>
			<xmin>173</xmin>
			<ymin>19</ymin>
			<xmax>190</xmax>
			<ymax>41</ymax>
		</bndbox>
	</object>
</annotation>
