<annotation>
	<folder>all_images_folder</folder>
	<filename>worker (780).jpg</filename>
	<path>C:\Users\nasir.shah\Desktop\all_images_folder\all_images_folder\worker (780).jpg</path>
	<source>
		<database>Unknown</database>
	</source>
	<size>
		<width>300</width>
		<height>168</height>
		<depth>3</depth>
	</size>
	<segmented>0</segmented>
	<object>
		<name>helmet</name>
		<pose>Unspecified</pose>
		<truncated>1</truncated>
		<difficult>0</difficult>
		<bndbox>
			<xmin>22</xmin>
			<ymin>1</ymin>
			<xmax>85</xmax>
			<ymax>45</ymax>
		</bndbox>
	</object>
	<object>
		<name>helmet</name>
		<pose>Unspecified</pose>
		<truncated>1</truncated>
		<difficult>0</difficult>
		<bndbox>
			<xmin>120</xmin>
			<ymin>1</ymin>
			<xmax>178</xmax>
			<ymax>38</ymax>
		</bndbox>
	</object>
	<object>
		<name>person with helmet</name>
		<pose>Unspecified</pose>
		<truncated>1</truncated>
		<difficult>0</difficult>
		<bndbox>
			<xmin>4</xmin>
			<ymin>1</ymin>
			<xmax>99</xmax>
			<ymax>162</ymax>
		</bndbox>
	</object>
	<object>
		<name>person with helmet</name>
		<pose>Unspecified</pose>
		<truncated>1</truncated>
		<difficult>0</difficult>
		<bndbox>
			<xmin>100</xmin>
			<ymin>1</ymin>
			<xmax>200</xmax>
			<ymax>129</ymax>
		</bndbox>
	</object>
</annotation>
