<annotation>
	<folder>dataset_images</folder>
	<filename>worker (541).jpg</filename>
	<path>D:\Workspace\YOLO_annotation\dataset_images\worker (541).jpg</path>
	<source>
		<database>Unknown</database>
	</source>
	<size>
		<width>265</width>
		<height>190</height>
		<depth>3</depth>
	</size>
	<segmented>0</segmented>
	<object>
		<name>helmet</name>
		<pose>Unspecified</pose>
		<truncated>0</truncated>
		<difficult>0</difficult>
		<bndbox>
			<xmin>51</xmin>
			<ymin>3</ymin>
			<xmax>89</xmax>
			<ymax>28</ymax>
		</bndbox>
	</object>
	<object>
		<name>helmet</name>
		<pose>Unspecified</pose>
		<truncated>0</truncated>
		<difficult>0</difficult>
		<bndbox>
			<xmin>8</xmin>
			<ymin>25</ymin>
			<xmax>46</xmax>
			<ymax>49</ymax>
		</bndbox>
	</object>
	<object>
		<name>helmet</name>
		<pose>Unspecified</pose>
		<truncated>0</truncated>
		<difficult>0</difficult>
		<bndbox>
			<xmin>127</xmin>
			<ymin>7</ymin>
			<xmax>171</xmax>
			<ymax>37</ymax>
		</bndbox>
	</object>
	<object>
		<name>helmet</name>
		<pose>Unspecified</pose>
		<truncated>0</truncated>
		<difficult>0</difficult>
		<bndbox>
			<xmin>212</xmin>
			<ymin>3</ymin>
			<xmax>257</xmax>
			<ymax>36</ymax>
		</bndbox>
	</object>
	<object>
		<name>person with helmet</name>
		<pose>Unspecified</pose>
		<truncated>1</truncated>
		<difficult>0</difficult>
		<bndbox>
			<xmin>1</xmin>
			<ymin>25</ymin>
			<xmax>66</xmax>
			<ymax>189</ymax>
		</bndbox>
	</object>
	<object>
		<name>person with helmet</name>
		<pose>Unspecified</pose>
		<truncated>0</truncated>
		<difficult>0</difficult>
		<bndbox>
			<xmin>106</xmin>
			<ymin>7</ymin>
			<xmax>181</xmax>
			<ymax>189</ymax>
		</bndbox>
	</object>
	<object>
		<name>person with helmet</name>
		<pose>Unspecified</pose>
		<truncated>0</truncated>
		<difficult>0</difficult>
		<bndbox>
			<xmin>41</xmin>
			<ymin>4</ymin>
			<xmax>90</xmax>
			<ymax>72</ymax>
		</bndbox>
	</object>
	<object>
		<name>person with helmet</name>
		<pose>Unspecified</pose>
		<truncated>1</truncated>
		<difficult>0</difficult>
		<bndbox>
			<xmin>182</xmin>
			<ymin>2</ymin>
			<xmax>265</xmax>
			<ymax>189</ymax>
		</bndbox>
	</object>
</annotation>
